bytebeam/__init__.py
bytebeam/cli.py
bytebeam/const.py
bytebeam/transfer.py
bytebeam/utils.py
bytebeam-0.1.1.dist-info/METADATA
bytebeam-0.1.1.dist-info/WHEEL
bytebeam-0.1.1.dist-info/entry_points.txt
bytebeam-0.1.1.dist-info/top_level.txt
bytebeam-0.1.1.dist-info/RECORD
