Metadata-Version: 2.4
Name: bytebeam
Version: 0.1.1
Summary: CLI File transfer tool over local network
Author: Dipanshu Tiwari
Author-email: dipanshutiwari115@gmail.com
Maintainer: Dipanshu Tiwari
Maintainer-email: dipanshutiwari115@gmail.com
Classifier: Programming Language :: Python :: 3
Classifier: License :: OSI Approved :: MIT License
Classifier: Operating System :: POSIX :: Linux
Classifier: Environment :: Console
Classifier: Intended Audience :: Developers
Requires-Python: >=3.6
Dynamic: author
Dynamic: author-email
Dynamic: classifier
Dynamic: description
Dynamic: description-content-type
Dynamic: maintainer
Dynamic: maintainer-email
Dynamic: requires-python
Dynamic: summary
